swiss_toys/__init__.py
swiss_toys/date_utils.py
swiss_toys/file_utils.py
swiss_toys/string_utils.py
swiss_toys-0.0.1.dist-info/METADATA
swiss_toys-0.0.1.dist-info/WHEEL
swiss_toys-0.0.1.dist-info/top_level.txt
swiss_toys-0.0.1.dist-info/RECORD
