Metadata-Version: 2.1
Name: swiss_toys
Version: 0.0.1
Summary: 一个实用的Python工具箱
Home-page: https://github.com/fmyblack/swiss_toys
Author: azai
Author-email: fmyblack@gmail.com
Classifier: Programming Language :: Python :: 3
Classifier: License :: OSI Approved :: MIT License
Classifier: Operating System :: OS Independent
Requires-Python: >=3.6
